garf_youtube_data_api/__init__.py
garf_youtube_data_api/api_clients.py
garf_youtube_data_api/exceptions.py
garf_youtube_data_api/query_editor.py
garf_youtube_data_api/report_fetcher.py
garf_youtube_data_api/simulator.py
garf_youtube_data_api/telemetry.py
garf_youtube_data_api/builtins/__init__.py
garf_youtube_data_api/builtins/channel_videos.py
garf_youtube_data_api-0.0.13.dist-info/METADATA
garf_youtube_data_api-0.0.13.dist-info/WHEEL
garf_youtube_data_api-0.0.13.dist-info/entry_points.txt
garf_youtube_data_api-0.0.13.dist-info/top_level.txt
garf_youtube_data_api-0.0.13.dist-info/RECORD
