Metadata-Version: 2.4
Name: garf-youtube-data-api
Version: 0.0.13
Summary: description
Author-email: Andrei Markin <amarkin@google.com>, "Google Inc. (gTech gPS CSE team)" <no-reply@google.com>
License: Apache 2.0
Classifier: Development Status :: 4 - Beta
Classifier: Programming Language :: Python
Requires-Python: >=3.8
Requires-Dist: garf-core[pandas]
Requires-Dist: garf-io
Requires-Dist: google-api-python-client
